kana2p/__init__.py
kana2p/const.py
kana2p/conversion.py
kana2p/py.typed
kana2p-0.1.2.dist-info/METADATA
kana2p-0.1.2.dist-info/WHEEL
kana2p-0.1.2.dist-info/licenses/LICENSE
kana2p-0.1.2.dist-info/RECORD
