Metadata-Version: 2.4
Name: kana2p
Version: 0.1.2
Summary: Japanese Katakana-Phonemes Conversion
Project-URL: repository, https://github.com/haruhisa-enomoto/kana2p
Project-URL: homepage, https://github.com/haruhisa-enomoto/kana2p
Author-email: Haruhisa Enomoto <73296681+haruhisa-enomoto@users.noreply.github.com>
License: MIT License
License-File: LICENSE
Classifier: Development Status :: 3 - Alpha
Classifier: Intended Audience :: Developers
Classifier: License :: OSI Approved :: MIT License
Classifier: Programming Language :: Python :: 3
Classifier: Programming Language :: Python :: 3 :: Only
Classifier: Programming Language :: Python :: 3.8
Classifier: Programming Language :: Python :: 3.9
Classifier: Programming Language :: Python :: 3.10
Classifier: Programming Language :: Python :: 3.11
Classifier: Programming Language :: Python :: 3.12
Classifier: Programming Language :: Python :: 3.13
Classifier: Topic :: Software Development :: Build Tools
Requires-Python: >=3.8
